aave/__init__.py
aave/__main__.py
aave/main.py
aave/packages.py
aave/types.py
aave/v3.py
aave-0.0.0.dist-info/licenses/LICENSE
aave-0.0.0.dist-info/METADATA
aave-0.0.0.dist-info/WHEEL
aave-0.0.0.dist-info/entry_points.txt
aave-0.0.0.dist-info/top_level.txt
aave-0.0.0.dist-info/RECORD
