Metadata-Version: 2.4
Name: aave
Version: 0.0.0
Summary: Ape SDK for interacting with Aave protocols
Author-email: ApeWorX LTD <admin@apeworx.io>
License-Expression: Apache-2.0
Project-URL: Repository, https://github.com/ApeWorX/aave-sdk.git
Project-URL: Issues, https://github.com/ApeWorX/aave-sdk/issues
Keywords: ethereum,ape,aave,defi
Classifier: Development Status :: 3 - Alpha
Classifier: Intended Audience :: Developers
Classifier: Natural Language :: English
Classifier: Operating System :: MacOS
Classifier: Operating System :: POSIX
Classifier: Programming Language :: Python :: 3
Classifier: Programming Language :: Python :: 3.10
Classifier: Programming Language :: Python :: 3.11
Classifier: Programming Language :: Python :: 3.12
Classifier: Programming Language :: Python :: 3.13
Classifier: Programming Language :: Python :: 3.14
Requires-Python: >=3.10
License-File: LICENSE
Requires-Dist: ape-tokens<1,>=0.8
Requires-Dist: eth-ape<1.0,>=0.8.43
Dynamic: license-file
